setup.py
pycovjson/__init__.py
pycovjson/convert.py
pycovjson/model.py
pycovjson/read_netcdf.py
pycovjson/write.py
pycovjson/writeNetCDF.py
pycovjson/write_netcdf.py
pycovjson.egg-info/PKG-INFO
pycovjson.egg-info/SOURCES.txt
pycovjson.egg-info/dependency_links.txt
pycovjson.egg-info/entry_points.txt
pycovjson.egg-info/namespace_packages.txt
pycovjson.egg-info/requires.txt
pycovjson.egg-info/top_level.txt
pycovjson.egg-info/zip-safe
pycovjson/cli/__init__.py
pycovjson/cli/convert.py
pycovjson/cli/viewer.py
pycovjson/test/__init__.py
pycovjson/test/test.py