Metadata-Version: 1.1
Name: pycovjson
Version: 0.3.9
Summary: Create CovJSON files from common scientific data formats
Home-page: https://github.com/Reading-eScience-Centre/pycovjson
Author: rileywilliams
Author-email: resc@reading.ac.uk
License: Copyright :: University of Reading
Download-URL: http://pypi.python.org/pypi/pycovjson/
Keywords: dataset,coverage,covjson
Platform: UNKNOWN
Classifier: Environment :: Console
Classifier: Intended Audience :: Developers
Classifier: Intended Audience :: Information Technology
Classifier: Intended Audience :: Science/Research
Classifier: Topic :: Scientific/Engineering
Classifier: Development Status :: 4 - Beta
Classifier: License :: OSI Approved :: BSD License
Classifier: Operating System :: OS Independent
Classifier: Programming Language :: Python :: 3
Classifier: Topic :: Internet :: WWW/HTTP
Classifier: Topic :: Software Development :: Libraries :: Python Modules
